{
  "version": "1",
  "cognitoConfig": {
    "identityPoolName": "amplifyreactauthtemp456931ae_identitypool_456931ae",
    "allowUnauthenticatedIdentities": false,
    "resourceNameTruncated": "amplif456931ae",
    "userPoolName": "amplifyreactauthtemp456931ae_userpool_456931ae",
    "autoVerifiedAttributes": [
      "email"
    ],
    "mfaConfiguration": "OFF",
    "mfaTypes": [
      "SMS Text Message"
    ],
    "smsAuthenticationMessage": "Your authentication code is {####}",
    "smsVerificationMessage": "Your verification code is {####}",
    "emailVerificationSubject": "Your verification code",
    "emailVerificationMessage": "Your verification code is {####}",
    "defaultPasswordPolicy": false,
    "passwordPolicyMinLength": 8,
    "passwordPolicyCharacters": [],
    "requiredAttributes": [
      "email"
    ],
    "aliasAttributes": [],
    "userpoolClientGenerateSecret": false,
    "userpoolClientRefreshTokenValidity": 30,
    "userpoolClientWriteAttributes": [
      "email"
    ],
    "userpoolClientReadAttributes": [
      "email"
    ],
    "userpoolClientLambdaRole": "amplif456931ae_userpoolclient_lambda_role",
    "userpoolClientSetAttributes": false,
    "sharedId": "456931ae",
    "resourceName": "amplifyreactauthtemp456931ae",
    "authSelections": "identityPoolAndUserPool",
    "useDefault": "defaultSocial",
    "usernameAttributes": [
      "email"
    ],
    "userPoolGroupList": [],
    "serviceName": "Cognito",
    "usernameCaseSensitive": false,
    "useEnabledMfas": true,
    "authRoleArn": {
      "Fn::GetAtt": [
        "AuthRole",
        "Arn"
      ]
    },
    "unauthRoleArn": {
      "Fn::GetAtt": [
        "UnauthRole",
        "Arn"
      ]
    },
    "breakCircularDependency": true,
    "dependsOn": [],
    "hostedUI": true,
    "hostedUIDomainName": "amplifyreactauthtemp5b171adb-5b171adb",
    "authProvidersUserPool": [
      "Facebook",
      "Google"
    ],
    "hostedUIProviderMeta": "[{\"ProviderName\":\"Facebook\",\"authorize_scopes\":\"email,public_profile\",\"AttributeMapping\":{\"email\":\"email\",\"username\":\"id\"}},{\"ProviderName\":\"Google\",\"authorize_scopes\":\"openid email profile\",\"AttributeMapping\":{\"email\":\"email\",\"username\":\"sub\"}}]",
    "oAuthMetadata": "{\"AllowedOAuthFlows\":[\"code\"],\"AllowedOAuthScopes\":[\"phone\",\"email\",\"openid\",\"profile\",\"aws.cognito.signin.user.admin\"],\"CallbackURLs\":[\"http://localhost:3000/\",\"https://master.d2k0z3rns6w91v.amplifyapp.com/\"],\"LogoutURLs\":[\"http://localhost:3000/\",\"https://master.d2k0z3rns6w91v.amplifyapp.com/\"]}",
    "authProviders": []
  }
}